mospy/Account.py
mospy/Transaction.py
mospy/__init__.py
mospy/utils.py
mospy/_transactions/__init__.py
mospy/_transactions/_delegate.py
mospy/_transactions/_transfer.py
mospy/_transactions/_undelegate.py
mospy/_transactions/_withdraw_reward.py
mospy/clients/GRPCClient.py
mospy/clients/HTTPClient.py
mospy/clients/__init__.py
mospy/exceptions/clients.py
mospy/protobuf/GenericProtobuf.py
mospy_wallet-0.6.0.dist-info/METADATA
mospy_wallet-0.6.0.dist-info/WHEEL
mospy_wallet-0.6.0.dist-info/RECORD
